{
	"name": "trigger1",
	"properties": {
		"annotations": [],
		"runtimeState": "Started",
		"pipeline": {
			"pipelineReference": {
				"referenceName": "PL_LOOKUP",
				"type": "PipelineReference"
			}
		},
		"type": "TumblingWindowTrigger",
		"typeProperties": {
			"frequency": "Hour",
			"interval": 24,
			"startTime": "2023-09-09T11:00:00Z",
			"endTime": "2023-09-21T11:01:00Z",
			"delay": "00:00:00",
			"maxConcurrency": 50,
			"retryPolicy": {
				"intervalInSeconds": 30
			},
			"dependsOn": []
		}
	}
}